iam_role_assumer/__init__.py
iam_role_assumer/command.py
iam_role_assumer-0.2.0.dist-info/LICENSE
iam_role_assumer-0.2.0.dist-info/METADATA
iam_role_assumer-0.2.0.dist-info/WHEEL
iam_role_assumer-0.2.0.dist-info/entry_points.txt
iam_role_assumer-0.2.0.dist-info/top_level.txt
iam_role_assumer-0.2.0.dist-info/RECORD
